cointables/__init__.py
cointables/main.py
cointables-0.1.2.dist-info/METADATA
cointables-0.1.2.dist-info/WHEEL
cointables-0.1.2.dist-info/LICENSE
cointables-0.1.2.dist-info/RECORD
