Metadata-Version: 2.1
Name: cointables
Version: 0.1.2
Summary: 
Author: andrewrgarcia
Author-email: garcia.gtr@gmail.com
Requires-Python: >=3.8,<4.0
Classifier: Programming Language :: Python :: 3
Classifier: Programming Language :: Python :: 3.8
Classifier: Programming Language :: Python :: 3.9
Classifier: Programming Language :: Python :: 3.10
Classifier: Programming Language :: Python :: 3.11
Requires-Dist: datetime (>=5.1,<6.0)
Requires-Dist: numpy (>=1.24.2,<2.0.0)
Requires-Dist: pandas (>=2.0.0,<3.0.0)
